adijif/__init__.py
adijif/adijif.py
adijif/cli.py
adijif/common.py
adijif/draw.py
adijif/gekko_trans.py
adijif/jesd.py
adijif/solvers.py
adijif/system.py
adijif/system_draw.py
adijif/types.py
adijif/utils.py
adijif/clocks/__init__.py
adijif/clocks/ad9523.py
adijif/clocks/ad9523_1_bf.py
adijif/clocks/ad9528.py
adijif/clocks/ad9528_bf.py
adijif/clocks/ad9545.py
adijif/clocks/clock.py
adijif/clocks/hmc7044.py
adijif/clocks/hmc7044_bf.py
adijif/clocks/ltc6952.py
adijif/clocks/ltc6952_bf.py
adijif/clocks/ltc6953.py
adijif/converters/__init__.py
adijif/converters/ad9081.py
adijif/converters/ad9081_dp.py
adijif/converters/ad9081_util.py
adijif/converters/ad9084.py
adijif/converters/ad9084_dp.py
adijif/converters/ad9084_draw.py
adijif/converters/ad9084_util.py
adijif/converters/ad9088_dp.py
adijif/converters/ad9144.py
adijif/converters/ad9144_bf.py
adijif/converters/ad9680.py
adijif/converters/ad9680_bf.py
adijif/converters/ad9680_draw.py
adijif/converters/adc.py
adijif/converters/adrv9009.py
adijif/converters/adrv9009_bf.py
adijif/converters/adrv9009_util.py
adijif/converters/converter.py
adijif/converters/dac.py
adijif/converters/resources/AD9084_JTX_JRX.xlsx
adijif/converters/resources/ad9081_JRx_204B.csv
adijif/converters/resources/ad9081_JRx_204C.csv
adijif/converters/resources/ad9081_JTx_204B.csv
adijif/converters/resources/ad9081_JTx_204C.csv
adijif/converters/resources/full_rx_mode_table_ad9081.csv
adijif/converters/resources/full_tx_mode_table_ad9081.csv
adijif/fpgas/__init__.py
adijif/fpgas/fpga.py
adijif/fpgas/xilinx/__init__.py
adijif/fpgas/xilinx/bf.py
adijif/fpgas/xilinx/pll.py
adijif/fpgas/xilinx/sevenseries.py
adijif/fpgas/xilinx/ultrascaleplus.py
adijif/fpgas/xilinx/xilinx_draw.py
adijif/plls/__init__.py
adijif/plls/adf4030.py
adijif/plls/adf4371.py
adijif/plls/adf4382.py
adijif/plls/pll.py
adijif/sys/__init__.py
adijif/sys/s_plls.py
adijif/tools/explorer/PyADI-JIF_logo.png
adijif/tools/explorer/cli.py
adijif/tools/explorer/main.py
pyadi_jif-0.1.4.dist-info/licenses/AUTHORS.rst
pyadi_jif-0.1.4.dist-info/licenses/LICENSE
pyadi_jif-0.1.4.dist-info/METADATA
pyadi_jif-0.1.4.dist-info/WHEEL
pyadi_jif-0.1.4.dist-info/entry_points.txt
pyadi_jif-0.1.4.dist-info/top_level.txt
pyadi_jif-0.1.4.dist-info/RECORD
