Metadata-Version: 2.4
Name: pyadi-jif
Version: 0.1.4
Summary: Python interface and configurator for ADI JESD Interface Framework
Author-email: "Travis F. Collins" <travis.collins@analog.com>
Maintainer: Analog Devices, Inc.
Maintainer-email: Travis Collins <travis.collins@analog.com>
License: EPL-2.0
Classifier: Programming Language :: Python
Classifier: Programming Language :: Python :: 3
Classifier: Programming Language :: Python :: 3 :: Only
Classifier: Programming Language :: Python :: 3.9
Requires-Python: >=3.9
License-File: LICENSE
License-File: AUTHORS.rst
Requires-Dist: numpy
Requires-Dist: openpyxl>=3.1.3
Requires-Dist: pandas>=1.1.5
Provides-Extra: cplex
Requires-Dist: cplex; extra == "cplex"
Requires-Dist: docplex; extra == "cplex"
Provides-Extra: gekko
Requires-Dist: gekko; extra == "gekko"
Provides-Extra: draw
Requires-Dist: pyd2lang-native==0.0.3; extra == "draw"
Provides-Extra: tools
Requires-Dist: streamlit; extra == "tools"
Dynamic: license-file
